.travis.yml
AUTHORS.rst
ChangeLog.rst
LICENSE.rst
MANIFEST.in
README.rst
appinfo.py
appveyor.yml
build.cmd
requirements-dev.txt
requirements.txt
setup.cfg
setup.py
setup_cxf.py
setup_py2exe.py
setup_utils.py
shippable.yml
tox.ini
appveyor/install.ps1
appveyor/run_with_compiler.cmd
doc/authors.rst
doc/changelog.rst
doc/conf.py
doc/index.rst
doc/license.rst
doc/readme.rst
doc/reference.rst
pythonhosted.org/doc.zip
pythonhosted.org/index.html
pythonhosted.org/redir2RTD.zip
tai/AUTHORS.txt
tai/ChangeLog.txt
tai/LICENSE.txt
tai/README.txt
tai/__init__.py
tai/appinfo.py
tai/tai.py
tai.egg-info/PKG-INFO
tai.egg-info/SOURCES.txt
tai.egg-info/dependency_links.txt
tai.egg-info/entry_points.txt
tai.egg-info/requires.txt
tai.egg-info/top_level.txt
tai/doc/.buildinfo
tai/doc/authors.html
tai/doc/changelog.html
tai/doc/genindex.html
tai/doc/index.html
tai/doc/license.html
tai/doc/objects.inv
tai/doc/py-modindex.html
tai/doc/readme.html
tai/doc/reference.html
tai/doc/search.html
tai/doc/searchindex.js
tai/doc/tai.pdf
tai/doc/_modules/index.html
tai/doc/_modules/tai.html
tai/doc/_sources/authors.txt
tai/doc/_sources/changelog.txt
tai/doc/_sources/index.txt
tai/doc/_sources/license.txt
tai/doc/_sources/readme.txt
tai/doc/_sources/reference.txt
tai/doc/_static/ajax-loader.gif
tai/doc/_static/alabaster.css
tai/doc/_static/basic.css
tai/doc/_static/comment-bright.png
tai/doc/_static/comment-close.png
tai/doc/_static/comment.png
tai/doc/_static/doctools.js
tai/doc/_static/down-pressed.png
tai/doc/_static/down.png
tai/doc/_static/file.png
tai/doc/_static/jquery-1.11.1.js
tai/doc/_static/jquery.js
tai/doc/_static/minus.png
tai/doc/_static/plus.png
tai/doc/_static/pygments.css
tai/doc/_static/searchtools.js
tai/doc/_static/underscore-1.3.1.js
tai/doc/_static/underscore.js
tai/doc/_static/up-pressed.png
tai/doc/_static/up.png
tai/doc/_static/websupport.js
test/test.rst
test/test_tai.py