Metadata-Version: 1.1
Name: tai
Version: 0.0.39
Summary: This module provides some technical indicators for analysing stocks.
Home-page: https://github.com/jcrmatos/tai
Author: Joao Carlos Roseta Matos
Author-email: jcrmatos@gmail.com
License: GNU General Public License v2 or later (GPLv2+)
Keywords: t,e,c,h,n,i,c,a,l, ,a,n,a,l,y,s,i,s, ,i,n,d,i,c,a,t,o,r,s
Platform: UNKNOWN
Classifier: Development Status :: 5 - Production/Stable
Classifier: Environment :: Console
Classifier: Intended Audience :: Developers
Classifier: Intended Audience :: End Users/Desktop
Classifier: Intended Audience :: Financial and Insurance Industry
Classifier: License :: OSI Approved :: GNU General Public License v2 or later (GPLv2+)
Classifier: Natural Language :: English
Classifier: Operating System :: OS Independent
Classifier: Programming Language :: Python
Classifier: Programming Language :: Python :: 2
Classifier: Programming Language :: Python :: 2.7
Classifier: Programming Language :: Python :: 3
Classifier: Programming Language :: Python :: 3.4
Classifier: Topic :: Office/Business :: Financial :: Investment
Classifier: Topic :: Software Development :: Libraries :: Python Modules
